momo/__init__.py
momo/model.py
momo/prototype.py
momo/system_models/__init__.py
momo/system_models/__item_apender.py
momo/system_models/system_models.py
momo/tests/__init__.py
momo/tests/set_pathes.py
momo/tests/test_model.py
momo/tests/test_multy_system_model.py
momo/tests/test_prototype.py
momo/tests/test_system_model.py
momo_morphological_modeling-1.3.0.dist-info/LICENSE
momo_morphological_modeling-1.3.0.dist-info/METADATA
momo_morphological_modeling-1.3.0.dist-info/WHEEL
momo_morphological_modeling-1.3.0.dist-info/top_level.txt
momo_morphological_modeling-1.3.0.dist-info/RECORD
