Metadata-Version: 2.2
Name: momo-morphological-modeling
Version: 1.3.0
Summary: MoMo is a module that does Morphological Modeling
Home-page: https://github.com/danylevych/MoMo
Author: Oleh Danylevych
Author-email: danylevych123@email.com
Classifier: Development Status :: 5 - Production/Stable
Classifier: Intended Audience :: Developers
Classifier: License :: OSI Approved :: MIT License
Classifier: Programming Language :: Python :: 3
Classifier: Programming Language :: Python :: 3.6
Classifier: Programming Language :: Python :: 3.7
Classifier: Programming Language :: Python :: 3.8
License-File: LICENSE
Dynamic: author
Dynamic: author-email
Dynamic: classifier
Dynamic: description
Dynamic: description-content-type
Dynamic: home-page
Dynamic: summary
